tinysom/__init__.py
tinysom/tinysom.py
tinysom-0.2.4.dist-info/METADATA
tinysom-0.2.4.dist-info/WHEEL
tinysom-0.2.4.dist-info/licenses/LICENSE
tinysom-0.2.4.dist-info/RECORD
