Metadata-Version: 2.4
Name: tinysom
Version: 0.2.4
Summary: Yet another Self-Organising Maps library
Project-URL: Homepage, https://github.com/MutaharChalmers/tinysom
Author-email: Mutahar Chalmers <mutahar.chalmers@gmail.com>
License: MIT License
License-File: LICENSE
Classifier: Development Status :: 4 - Beta
Classifier: Intended Audience :: Science/Research
Classifier: License :: OSI Approved :: MIT License
Classifier: Operating System :: OS Independent
Classifier: Programming Language :: Python :: 3
Classifier: Topic :: Scientific/Engineering
Requires-Python: >=3.8
Requires-Dist: matplotlib>=2.3
Requires-Dist: numpy>=1.18
Requires-Dist: scipy>=0.11
Requires-Dist: tqdm>=4.63
